AUTHORS.md
LICENSE.md
README.md
pyproject.toml
setup.cfg
setup.py
pyan/__init__.py
pyan/__main__.py
pyan/analyzer.py
pyan/anutils.py
pyan/callgraph.html
pyan/main.py
pyan/node.py
pyan/sphinx.py
pyan/visgraph.py
pyan/writers.py
pyan3new.egg-info/PKG-INFO
pyan3new.egg-info/SOURCES.txt
pyan3new.egg-info/dependency_links.txt
pyan3new.egg-info/entry_points.txt
pyan3new.egg-info/requires.txt
pyan3new.egg-info/top_level.txt
pyan3new.egg-info/zip-safe