Metadata-Version: 2.1
Name: pyan3new
Version: 1.2.1
Summary: Offline call graph generator for Python 3
Home-page: https://github.com/Technologicat/pyan
Author: Juha Jeronen
Author-email: juha.m.jeronen@gmail.com
License: GPL 2.0
Keywords: call-graph,static-code-analysis
Platform: Linux
Classifier: Development Status :: 4 - Beta
Classifier: Environment :: Console
Classifier: Intended Audience :: Developers
Classifier: License :: OSI Approved :: GNU General Public License v2 (GPLv2)
Classifier: Operating System :: POSIX :: Linux
Classifier: Programming Language :: Python
Classifier: Programming Language :: Python :: 3
Classifier: Programming Language :: Python :: 3.6
Classifier: Programming Language :: Python :: 3.7
Classifier: Topic :: Software Development
Provides: pyan
License-File: LICENSE.md
License-File: AUTHORS.md
